Workbook

Sheet README
A1: Daily Trade Recommendations Tracker
A2: Purpose: log the agent's daily picks (option scalp, intraday, short-term) and track outcomes.
A4: How to use
A5: 1. The agent appends one row per pick to 'Recommendations' (8:00 AM IST).
A6: 2. The agent (or you) mirrors each pick into 'Tracker' and updates Actual Entry, Exit Price, Exit Date, Status.
A7: 3. Blue font = input cells. Black = formulas (do not overwrite). Yellow rows = EXAMPLE rows: delete before real use.
A8: 4. 'Performance' and P&L / R-multiple columns recalculate automatically.
A9: 5. Edit limits (min risk:reward, max picks, capital, risk %) in 'Config'.
A11: Status values: Open, Not Triggered, T1 Hit, T2 Hit, SL Hit, Expired, Manual Exit
A12: Example values are illustrative only, not real recommendations or prices.
A13: Disclaimer: for personal research/education. Not investment advice. Trading, especially intraday and options, can cause substantial losses.

Sheet Config
A1: Parameter | B1: Value | C1: Note
A2: Trading capital (INR) | B2: 500000 | C2: Assumption: your input. Change to your actual capital.
A3: Risk per trade (% of capital) | B3: 0.01 | C3: Assumption: 1% default. Stored as fraction.
A4: Min risk:reward | B4: 1.5 | C4: Picks below this are rejected by the hook.
A5: Max option-scalp picks/day | B5: 2 | C5: Per your spec.
A6: Max intraday picks/day | B6: 2 | C6: Per your spec.
A7: Max short-term picks/day | B7: 2 | C7: Per your spec.
A8: Short-term max holding (days) | B8: 10 | C8: Assumption: after this, mark Expired.
A9: Min avg daily turnover (INR cr) | B9: 20 | C9: Assumption: liquidity filter for Nifty 500 scan.
A11: Risk amount per trade (INR) | B11: =B2*B3 -> 5000

Sheet Market_Context
A1: Date | B1: Gift Nifty | C1: Nifty Prev Close | D1: Implied Gap (pts) | E1: Implied Gap % | F1: S&P 500 % | G1: Nasdaq % | H1: Dow % | I1: Nikkei % | J1: Hang Seng % | K1: Crude (Brent) % | L1: USD/INR | M1: India VIX | N1: US VIX | O1: Day Bias | P1: Key Events / Notes
A2: 2026-01-05 | B2: 24550 | C2: 24480 | D2: =IF(OR(B2="",C2=""),"",B2-C2) -> 70 | E2: =IF(OR(B2="",C2=""),"",D2/C2) -> 0.0028594771 | F2: 0.004 | G2: 0.006 | H2: 0.002 | I2: -0.003 | J2: 0.001 | K2: -0.005 | L2: 85.2 | M2: 13.4 | N2: 16.1 | O2: Mild Bullish | P2: EXAMPLE: illustrative values only
D3: =IF(OR(B3="",C3=""),"",B3-C3) | E3: =IF(OR(B3="",C3=""),"",D3/C3)
D4: =IF(OR(B4="",C4=""),"",B4-C4) | E4: =IF(OR(B4="",C4=""),"",D4/C4)
D5: =IF(OR(B5="",C5=""),"",B5-C5) | E5: =IF(OR(B5="",C5=""),"",D5/C5)
D6: =IF(OR(B6="",C6=""),"",B6-C6) | E6: =IF(OR(B6="",C6=""),"",D6/C6)
D7: =IF(OR(B7="",C7=""),"",B7-C7) | E7: =IF(OR(B7="",C7=""),"",D7/C7)
D8: =IF(OR(B8="",C8=""),"",B8-C8) | E8: =IF(OR(B8="",C8=""),"",D8/C8)
D9: =IF(OR(B9="",C9=""),"",B9-C9) | E9: =IF(OR(B9="",C9=""),"",D9/C9)
D10: =IF(OR(B10="",C10=""),"",B10-C10) | E10: =IF(OR(B10="",C10=""),"",D10/C10)
D11: =IF(OR(B11="",C11=""),"",B11-C11) | E11: =IF(OR(B11="",C11=""),"",D11/C11)
D12: =IF(OR(B12="",C12=""),"",B12-C12) | E12: =IF(OR(B12="",C12=""),"",D12/C12)
D13: =IF(OR(B13="",C13=""),"",B13-C13) | E13: =IF(OR(B13="",C13=""),"",D13/C13)
D14: =IF(OR(B14="",C14=""),"",B14-C14) | E14: =IF(OR(B14="",C14=""),"",D14/C14)
... D399: =IF(OR(B399="",C399=""),"",B399-C399) | E399: =IF(OR(B399="",C399=""),"",D399/C399)

Sheet Recommendations
A1: ID | B1: Date | C1: Type | D1: Symbol | E1: Direction | F1: Instrument | G1: Strike / Expiry | H1: Entry / Trigger | I1: Stop Loss | J1: Target 1 | K1: Target 2 | L1: Risk:Reward (T1) | M1: Qty (by risk) | N1: Rationale | O1: Confidence (1-5) | P1: Valid Until
A2: 20260105-S1 | B2: 2026-01-05 | C2: Option Scalp | D2: NIFTY | E2: Buy | F2: CE | G2: 24600 / weekly | H2: 95 | I2: 75 | J2: 125 | K2: 150 | L2: =IF(OR(H2="",I2="",J2=""),"",IF(H2=I2,"",ABS(J2-H2)/ABS(H2-I2))) -> 1.5 | M2: =IF(OR(H2="",I2="",H2=I2),"",ROUNDDOWN(Config!$B$11/ABS(H2-I2),0)) -> 250 | N2: EXAMPLE: Gift Nifty +0.3%, holds above prior-day high after 9:30; buy only on trigger. | O2: 3 | P2: 2026-01-05
L3: =IF(OR(H3="",I3="",J3=""),"",IF(H3=I3,"",ABS(J3-H3)/ABS(H3-I3))) | M3: =IF(OR(H3="",I3="",H3=I3),"",ROUNDDOWN(Config!$B$11/ABS(H3-I3),0))
L4: =IF(OR(H4="",I4="",J4=""),"",IF(H4=I4,"",ABS(J4-H4)/ABS(H4-I4))) | M4: =IF(OR(H4="",I4="",H4=I4),"",ROUNDDOWN(Config!$B$11/ABS(H4-I4),0))
L5: =IF(OR(H5="",I5="",J5=""),"",IF(H5=I5,"",ABS(J5-H5)/ABS(H5-I5))) | M5: =IF(OR(H5="",I5="",H5=I5),"",ROUNDDOWN(Config!$B$11/ABS(H5-I5),0))
L6: =IF(OR(H6="",I6="",J6=""),"",IF(H6=I6,"",ABS(J6-H6)/ABS(H6-I6))) | M6: =IF(OR(H6="",I6="",H6=I6),"",ROUNDDOWN(Config!$B$11/ABS(H6-I6),0))
L7: =IF(OR(H7="",I7="",J7=""),"",IF(H7=I7,"",ABS(J7-H7)/ABS(H7-I7))) | M7: =IF(OR(H7="",I7="",H7=I7),"",ROUNDDOWN(Config!$B$11/ABS(H7-I7),0))
L8: =IF(OR(H8="",I8="",J8=""),"",IF(H8=I8,"",ABS(J8-H8)/ABS(H8-I8))) | M8: =IF(OR(H8="",I8="",H8=I8),"",ROUNDDOWN(Config!$B$11/ABS(H8-I8),0))
L9: =IF(OR(H9="",I9="",J9=""),"",IF(H9=I9,"",ABS(J9-H9)/ABS(H9-I9))) | M9: =IF(OR(H9="",I9="",H9=I9),"",ROUNDDOWN(Config!$B$11/ABS(H9-I9),0))
L10: =IF(OR(H10="",I10="",J10=""),"",IF(H10=I10,"",ABS(J10-H10)/ABS(H10-I10))) | M10: =IF(OR(H10="",I10="",H10=I10),"",ROUNDDOWN(Config!$B$11/ABS(H10-I10),0))
L11: =IF(OR(H11="",I11="",J11=""),"",IF(H11=I11,"",ABS(J11-H11)/ABS(H11-I11))) | M11: =IF(OR(H11="",I11="",H11=I11),"",ROUNDDOWN(Config!$B$11/ABS(H11-I11),0))
L12: =IF(OR(H12="",I12="",J12=""),"",IF(H12=I12,"",ABS(J12-H12)/ABS(H12-I12))) | M12: =IF(OR(H12="",I12="",H12=I12),"",ROUNDDOWN(Config!$B$11/ABS(H12-I12),0))
L13: =IF(OR(H13="",I13="",J13=""),"",IF(H13=I13,"",ABS(J13-H13)/ABS(H13-I13))) | M13: =IF(OR(H13="",I13="",H13=I13),"",ROUNDDOWN(Config!$B$11/ABS(H13-I13),0))
L14: =IF(OR(H14="",I14="",J14=""),"",IF(H14=I14,"",ABS(J14-H14)/ABS(H14-I14))) | M14: =IF(OR(H14="",I14="",H14=I14),"",ROUNDDOWN(Config!$B$11/ABS(H14-I14),0))
... L499: =IF(OR(H499="",I499="",J499=""),"",IF(H499=I499,"",ABS(J499-H499)/ABS(H499-I499))) | M499: =IF(OR(H499="",I499="",H499=I499),"",ROUNDDOWN(Config!$B$11/ABS(H499-I499),0))

Sheet Tracker
A1: ID | B1: Date | C1: Type | D1: Symbol | E1: Direction | F1: Planned Entry | G1: Stop Loss | H1: Target 1 | I1: Actual Entry | J1: Exit Price | K1: Exit Date | L1: Status | M1: P&L % | N1: R-Multiple | O1: Days Held | P1: Win? | Q1: Notes
A2: 20260105-S1 | B2: 2026-01-05 | C2: Option Scalp | D2: NIFTY | E2: Buy | F2: 95 | G2: 75 | H2: 125 | I2: 96 | J2: 124 | K2: 2026-01-05 | L2: T1 Hit | M2: =IF(OR(I2="",J2=""),"",IF(E2="Buy",(J2-I2)/I2,(I2-J2)/I2)) -> 0.29166667 | N2: =IF(OR(I2="",J2="",I2=G2),"",IF(E2="Buy",(J2-I2)/(I2-G2),(I2-J2)/(G2-I2))) -> 1.3333333 | O2: =IF(OR(B2="",K2=""),"",IFERROR(K2-B2,"")) -> 0 | P2: =IF(M2="","",IF(M2>0,1,0)) -> 1 | Q2: EXAMPLE: delete this row
M3: =IF(OR(I3="",J3=""),"",IF(E3="Buy",(J3-I3)/I3,(I3-J3)/I3)) | N3: =IF(OR(I3="",J3="",I3=G3),"",IF(E3="Buy",(J3-I3)/(I3-G3),(I3-J3)/(G3-I3))) | O3: =IF(OR(B3="",K3=""),"",IFERROR(K3-B3,"")) | P3: =IF(M3="","",IF(M3>0,1,0))
M4: =IF(OR(I4="",J4=""),"",IF(E4="Buy",(J4-I4)/I4,(I4-J4)/I4)) | N4: =IF(OR(I4="",J4="",I4=G4),"",IF(E4="Buy",(J4-I4)/(I4-G4),(I4-J4)/(G4-I4))) | O4: =IF(OR(B4="",K4=""),"",IFERROR(K4-B4,"")) | P4: =IF(M4="","",IF(M4>0,1,0))
M5: =IF(OR(I5="",J5=""),"",IF(E5="Buy",(J5-I5)/I5,(I5-J5)/I5)) | N5: =IF(OR(I5="",J5="",I5=G5),"",IF(E5="Buy",(J5-I5)/(I5-G5),(I5-J5)/(G5-I5))) | O5: =IF(OR(B5="",K5=""),"",IFERROR(K5-B5,"")) | P5: =IF(M5="","",IF(M5>0,1,0))
M6: =IF(OR(I6="",J6=""),"",IF(E6="Buy",(J6-I6)/I6,(I6-J6)/I6)) | N6: =IF(OR(I6="",J6="",I6=G6),"",IF(E6="Buy",(J6-I6)/(I6-G6),(I6-J6)/(G6-I6))) | O6: =IF(OR(B6="",K6=""),"",IFERROR(K6-B6,"")) | P6: =IF(M6="","",IF(M6>0,1,0))
M7: =IF(OR(I7="",J7=""),"",IF(E7="Buy",(J7-I7)/I7,(I7-J7)/I7)) | N7: =IF(OR(I7="",J7="",I7=G7),"",IF(E7="Buy",(J7-I7)/(I7-G7),(I7-J7)/(G7-I7))) | O7: =IF(OR(B7="",K7=""),"",IFERROR(K7-B7,"")) | P7: =IF(M7="","",IF(M7>0,1,0))
M8: =IF(OR(I8="",J8=""),"",IF(E8="Buy",(J8-I8)/I8,(I8-J8)/I8)) | N8: =IF(OR(I8="",J8="",I8=G8),"",IF(E8="Buy",(J8-I8)/(I8-G8),(I8-J8)/(G8-I8))) | O8: =IF(OR(B8="",K8=""),"",IFERROR(K8-B8,"")) | P8: =IF(M8="","",IF(M8>0,1,0))
M9: =IF(OR(I9="",J9=""),"",IF(E9="Buy",(J9-I9)/I9,(I9-J9)/I9)) | N9: =IF(OR(I9="",J9="",I9=G9),"",IF(E9="Buy",(J9-I9)/(I9-G9),(I9-J9)/(G9-I9))) | O9: =IF(OR(B9="",K9=""),"",IFERROR(K9-B9,"")) | P9: =IF(M9="","",IF(M9>0,1,0))
M10: =IF(OR(I10="",J10=""),"",IF(E10="Buy",(J10-I10)/I10,(I10-J10)/I10)) | N10: =IF(OR(I10="",J10="",I10=G10),"",IF(E10="Buy",(J10-I10)/(I10-G10),(I10-J10)/(G10-I10))) | O10: =IF(OR(B10="",K10=""),"",IFERROR(K10-B10,"")) | P10: =IF(M10="","",IF(M10>0,1,0))
M11: =IF(OR(I11="",J11=""),"",IF(E11="Buy",(J11-I11)/I11,(I11-J11)/I11)) | N11: =IF(OR(I11="",J11="",I11=G11),"",IF(E11="Buy",(J11-I11)/(I11-G11),(I11-J11)/(G11-I11))) | O11: =IF(OR(B11="",K11=""),"",IFERROR(K11-B11,"")) | P11: =IF(M11="","",IF(M11>0,1,0))
M12: =IF(OR(I12="",J12=""),"",IF(E12="Buy",(J12-I12)/I12,(I12-J12)/I12)) | N12: =IF(OR(I12="",J12="",I12=G12),"",IF(E12="Buy",(J12-I12)/(I12-G12),(I12-J12)/(G12-I12))) | O12: =IF(OR(B12="",K12=""),"",IFERROR(K12-B12,"")) | P12: =IF(M12="","",IF(M12>0,1,0))
M13: =IF(OR(I13="",J13=""),"",IF(E13="Buy",(J13-I13)/I13,(I13-J13)/I13)) | N13: =IF(OR(I13="",J13="",I13=G13),"",IF(E13="Buy",(J13-I13)/(I13-G13),(I13-J13)/(G13-I13))) | O13: =IF(OR(B13="",K13=""),"",IFERROR(K13-B13,"")) | P13: =IF(M13="","",IF(M13>0,1,0))
M14: =IF(OR(I14="",J14=""),"",IF(E14="Buy",(J14-I14)/I14,(I14-J14)/I14)) | N14: =IF(OR(I14="",J14="",I14=G14),"",IF(E14="Buy",(J14-I14)/(I14-G14),(I14-J14)/(G14-I14))) | O14: =IF(OR(B14="",K14=""),"",IFERROR(K14-B14,"")) | P14: =IF(M14="","",IF(M14>0,1,0))
... M999: =IF(OR(I999="",J999=""),"",IF(E999="Buy",(J999-I999)/I999,(I999-J999)/I999)) | N999: =IF(OR(I999="",J999="",I999=G999),"",IF(E999="Buy",(J999-I999)/(I999-G999),(I999-J999)/(G999-I999))) | O999: =IF(OR(B999="",K999=""),"",IFERROR(K999-B999,"")) | P999: =IF(M999="","",IF(M999>0,1,0))

Sheet Performance
A1: Type | B1: Closed Trades | C1: Wins | D1: Win Rate | E1: Avg P&L % | F1: Avg R-Multiple | G1: Total R | H1: Open Trades
A2: Option Scalp | B2: =COUNTIFS(Tracker!$C$2:$C$999,$A2,Tracker!$M$2:$M$999,"<>")-COUNTIFS(Tracker!$C$2:$C$999,$A2,Tracker!$M$2:$M$999,"") -> 1 | C2: =COUNTIFS(Tracker!$C$2:$C$999,$A2,Tracker!$P$2:$P$999,1) -> 1 | D2: =IF(B2=0,0,C2/B2) -> 1 | E2: =IFERROR(AVERAGEIFS(Tracker!$M$2:$M$999,Tracker!$C$2:$C$999,$A2),0) -> 0.29166667 | F2: =IFERROR(AVERAGEIFS(Tracker!$N$2:$N$999,Tracker!$C$2:$C$999,$A2),0) -> 1.3333333 | G2: =SUMIFS(Tracker!$N$2:$N$999,Tracker!$C$2:$C$999,$A2) -> 1.3333333 | H2: =COUNTIFS(Tracker!$C$2:$C$999,$A2,Tracker!$L$2:$L$999,"Open") -> 0
A3: Intraday | B3: =COUNTIFS(Tracker!$C$2:$C$999,$A3,Tracker!$M$2:$M$999,"<>")-COUNTIFS(Tracker!$C$2:$C$999,$A3,Tracker!$M$2:$M$999,"") -> 0 | C3: =COUNTIFS(Tracker!$C$2:$C$999,$A3,Tracker!$P$2:$P$999,1) -> 0 | D3: =IF(B3=0,0,C3/B3) -> 0 | E3: =IFERROR(AVERAGEIFS(Tracker!$M$2:$M$999,Tracker!$C$2:$C$999,$A3),0) -> 0 | F3: =IFERROR(AVERAGEIFS(Tracker!$N$2:$N$999,Tracker!$C$2:$C$999,$A3),0) -> 0 | G3: =SUMIFS(Tracker!$N$2:$N$999,Tracker!$C$2:$C$999,$A3) -> 0 | H3: =COUNTIFS(Tracker!$C$2:$C$999,$A3,Tracker!$L$2:$L$999,"Open") -> 0
A4: Short-term | B4: =COUNTIFS(Tracker!$C$2:$C$999,$A4,Tracker!$M$2:$M$999,"<>")-COUNTIFS(Tracker!$C$2:$C$999,$A4,Tracker!$M$2:$M$999,"") -> 0 | C4: =COUNTIFS(Tracker!$C$2:$C$999,$A4,Tracker!$P$2:$P$999,1) -> 0 | D4: =IF(B4=0,0,C4/B4) -> 0 | E4: =IFERROR(AVERAGEIFS(Tracker!$M$2:$M$999,Tracker!$C$2:$C$999,$A4),0) -> 0 | F4: =IFERROR(AVERAGEIFS(Tracker!$N$2:$N$999,Tracker!$C$2:$C$999,$A4),0) -> 0 | G4: =SUMIFS(Tracker!$N$2:$N$999,Tracker!$C$2:$C$999,$A4) -> 0 | H4: =COUNTIFS(Tracker!$C$2:$C$999,$A4,Tracker!$L$2:$L$999,"Open") -> 0
A5: All | B5: =SUM(B2:B4) -> 1 | C5: =SUM(C2:C4) -> 1 | D5: =IF(B5=0,0,C5/B5) -> 1 | E5: =IFERROR(AVERAGE(Tracker!$M$2:$M$999),0) -> 0.29166667 | F5: =IFERROR(AVERAGE(Tracker!$N$2:$N$999),0) -> 1.3333333 | G5: =SUM(G2:G4) -> 1.3333333 | H5: =SUM(H2:H4) -> 0
A7: Note: Closed = rows with a computed P&L. Includes the yellow EXAMPLE row until you delete it.
